llm_api_open-2.4.7.data/data/LICENSE
llm_api_open-2.4.7.data/data/README.md
llm_api_open-2.4.7.data/data/assistantGetLastMessage.js
llm_api_open-2.4.7.data/data/chatgpt.json
llm_api_open-2.4.7.data/data/chatgpt_api.py
llm_api_open-2.4.7.data/data/conversationManage.js
llm_api_open-2.4.7.data/data/conversationParser.js
llm_api_open-2.4.7.data/data/conversationSearch.js
llm_api_open-2.4.7.data/data/ms_copilot.json
llm_api_open-2.4.7.data/data/ms_copilot_api.py
llm_api_open-2.4.7.data/data/proxy_extension.py
lmao/__init__.py
lmao/_version.py
lmao/external_api.py
lmao/main.py
lmao/module_wrapper.py
lmao/chatgpt/assistantGetLastMessage.js
lmao/chatgpt/chatgpt_api.py
lmao/chatgpt/conversationSearch.js
lmao/chatgpt/proxy_extension.py
lmao/ms_copilot/conversationManage.js
lmao/ms_copilot/conversationParser.js
lmao/ms_copilot/ms_copilot_api.py
lmao/ms_copilot/proxy_extension.py
llm_api_open-2.4.7.dist-info/LICENSE
llm_api_open-2.4.7.dist-info/METADATA
llm_api_open-2.4.7.dist-info/WHEEL
llm_api_open-2.4.7.dist-info/entry_points.txt
llm_api_open-2.4.7.dist-info/top_level.txt
llm_api_open-2.4.7.dist-info/RECORD
