Metadata-Version: 2.1
Name: llm-api-open
Version: 2.4.7
Summary: Unofficial open APIs for popular LLMs with self-hosted redirect capability
Home-page: https://github.com/F33RNI/LlM-Api-Open
Author: Fern Lane
License: MIT License
Project-URL: Bug Report, https://github.com/F33RNI/LlM-Api-Open/issues/new
Classifier: Development Status :: 4 - Beta
Classifier: Environment :: Console
Classifier: Framework :: Flask
Classifier: Intended Audience :: Developers
Classifier: Intended Audience :: Science/Research
Classifier: Intended Audience :: Education
Classifier: Intended Audience :: Information Technology
Classifier: Intended Audience :: System Administrators
Classifier: License :: OSI Approved :: MIT License
Classifier: Programming Language :: JavaScript
Classifier: Programming Language :: Python
Classifier: Programming Language :: Python :: 3
Classifier: Programming Language :: Python :: 3.9
Classifier: Programming Language :: Python :: 3.10
Classifier: Programming Language :: Python :: 3.11
Classifier: Topic :: Internet
Classifier: Topic :: Internet :: WWW/HTTP
Classifier: Topic :: Software Development
Classifier: Topic :: Software Development :: Libraries
Classifier: Topic :: Software Development :: Libraries :: Application Frameworks
Classifier: Topic :: Software Development :: Libraries :: Python Modules
License-File: LICENSE
Requires-Dist: selenium >=4.18.1
Requires-Dist: undetected-chromedriver >=3.5.5
Requires-Dist: beautifulsoup4 >=4.12.3
Requires-Dist: markdownify >=0.11.6
Requires-Dist: Flask <4,>=3
Requires-Dist: Flask-Limiter <4,>=3
